jsonrpc/__init__.py
jsonrpc/types/__init__.py
jsonrpc/types/case.py
jsonrpc/types/client_error.py
jsonrpc/types/constants.py
jsonrpc/types/request.py
jsonrpc/types/response.py
jsonrpc/types/server_error.py
jsonrpc/utils/__init__.py
jsonrpc/utils/fp.py
jsonrpc/ws/__init__.py
jsonrpc/ws/async_live_queue.py
jsonrpc/ws/connection.py
jsonrpc/ws/response_queue.py
jsonrpc/ws/subscription_manager.py
bx_jsonrpc_py-0.2.0.dist-info/LICENSE
bx_jsonrpc_py-0.2.0.dist-info/METADATA
bx_jsonrpc_py-0.2.0.dist-info/WHEEL
bx_jsonrpc_py-0.2.0.dist-info/top_level.txt
bx_jsonrpc_py-0.2.0.dist-info/RECORD
