Metadata-Version: 2.1
Name: bx-jsonrpc-py
Version: 0.2.0
Summary: JSON-RPC Python client with streaming support
Home-page: https://github.com/bloXroute-Labs/bx-jsonrpc-py
Author: bloXroute Labs
Keywords: jsonrpc,websockets,ws,notification,stream
Classifier: Programming Language :: Python :: 3
License-File: LICENSE
Requires-Dist: pyhumps
Requires-Dist: websockets
